[
  { "end": 0, "check": [] },
  { "end": 1, "check": [] },
  { "end": 2, "check": [] },
  { "end": 3, "check": [] },
  { "end": 4, "check": [] },
  { "end": 5, "check": [] },
  { "end": 6, "check": [] },
  { "end": 7, "check": [] },
  { "end": 8, "check": [] },
  { "end": 9, "check": [] },
  { "end": 10, "check": [] },
  { "end": 11, "check": [] },
  { "end": 12, "check": [] },
  { "end": 13, "check": [] },
  { "end": 15, "check": [14] },
  { "end": 16, "check": [] },
  { "end": 18, "check": [17] },
  { "end": 19, "check": [] },
  { "end": 20, "check": [] }
]
